ndcsv/__init__.py
ndcsv/proper_unstack.py
ndcsv/py.typed
ndcsv/read.py
ndcsv/write.py
ndcsv/tests/__init__.py
ndcsv/tests/test_io.py
ndcsv/tests/test_pandas.py
ndcsv/tests/test_proper_unstack.py
ndcsv/tests/test_read.py
ndcsv/tests/test_roundtrip.py
ndcsv/tests/test_write.py
ndcsv-1.3.0.dist-info/METADATA
ndcsv-1.3.0.dist-info/WHEEL
ndcsv-1.3.0.dist-info/licenses/LICENSE
ndcsv-1.3.0.dist-info/RECORD
